CHANGELOG.md
LICENSE
MANIFEST.in
README.md
setup.cfg
setup.py
pip_services3_redis/__init__.py
pip_services3_redis.egg-info/PKG-INFO
pip_services3_redis.egg-info/SOURCES.txt
pip_services3_redis.egg-info/dependency_links.txt
pip_services3_redis.egg-info/requires.txt
pip_services3_redis.egg-info/top_level.txt
pip_services3_redis.egg-info/zip-safe
pip_services3_redis/build/DefaultRedisFactory.py
pip_services3_redis/build/__init__.py
pip_services3_redis/cache/RedisCache.py
pip_services3_redis/cache/__init__.py
pip_services3_redis/lock/RedisLock.py
pip_services3_redis/lock/__init__.py
test/cache/__init__.py
test/cache/test_RedisCache.py
test/fixtures/CacheFixture.py
test/fixtures/LockFixture.py
test/fixtures/__init__.py
test/lock/__init__.py
test/lock/test_RedisLock.py